pyobihai/__init__.py
pyobihai/const.py
pyobihai/parsing.py
tests/__init__.py
tests/conftest.py
tests/const.py
tests/test_pyobihai.py
pyobihai-1.4.2.dist-info/LICENSE
pyobihai-1.4.2.dist-info/METADATA
pyobihai-1.4.2.dist-info/WHEEL
pyobihai-1.4.2.dist-info/top_level.txt
pyobihai-1.4.2.dist-info/RECORD
