Metadata-Version: 2.1
Name: pyobihai
Version: 1.4.2
Summary: A Python wrapper for Obihai
Home-page: https://github.com/ejpenney/pyobihai
Author: Emory Penney
Author-email: treadstoneit@gmail.com
License: MIT
Classifier: Programming Language :: Python :: 3
Classifier: License :: OSI Approved :: MIT License
Classifier: Operating System :: OS Independent
License-File: LICENSE
